html2pdf3.py
lib/ConfigManager.py
lib/DatabaseManager.py
lib/DatabaseSchemaReader.py
lib/DocumentProcessor.py
lib/MonitorService.py
lib/__init__.py
lib/check_environment.py
lib/check_pdf_file.py
lib/check_printer_queue.py
lib/config.py
lib/config_loader.py
lib/create_new_zo.py
lib/create_zo_from_existing.py
lib/display_utils.py
lib/document_printer.py
lib/document_utils.py
lib/environment.py
lib/file_handler.py
lib/file_utils.py
lib/format_date.py
lib/format_number.py
lib/get_all_printers.py
lib/get_all_tables.py
lib/get_default_printer.py
lib/get_next_zo_number.py
lib/get_printer_info.py
lib/get_printer_ip.py
lib/get_zo_documents.py
lib/html_generator.py
lib/load_config.py
lib/log_conf.py
lib/log_config.py
lib/logger.py
lib/move_to_printed.py
lib/moved_to_printed.py
lib/order_processor.py
lib/order_processor2.py
lib/pdf_generator.py
lib/print_document.py
lib/print_document_by_printer.py
lib/print_tables.py
lib/print_with_adobe.py
lib/print_with_ghostscript.py
lib/printer.py
lib/printer_utils.py
lib/set_default_printer.py
lib/sql_queries.py
lib/test_printer_connection.py
lib/update_config.py
lib/wait_for_print_job.py
lib/zo_creator.py
lib/zo_document_utils.py
thermal_printer.py
waproprint/__init__.py
zpl/README.md
zpl/TUTORIAL.md
zpl/__init__.py
zpl/convert.py
zpl/example_order.py
zpl/html2zpl.py
zpl/html2zpl2pdf.py
zpl/html2zpl2print.py
zpl/html_to_zpl.py
zpl/index.html
zpl/network_printer.py
zpl/print.py
zpl/repair.py
zpl/requirements.txt
zpl/test.py
zpl/validate.py
zpl/zpl/12.zpl
zpl/zpl/28.zpl
zpl/zpl/8.zpl
zpl/zpl/88.zpl
zpl/zpl/etykieta_20.0cm.zpl
zpl/zpl/etykieta_20.0cm_203dpi_4.0cali.zpl
zpl/zpl/etykieta_30.0cm_300dpi_4.0cali.zpl
zpl/zpl/my_label.zpl
zpl/zpl30cm.py
zpl/zpl_calculate_dimensions.py
zpl/zpl_converter.py
zpl/zpl_encoding.py
zpl/zpl_file.py
zpl/zpl_html_processor.py
zpl/zpl_parse_html.py
zpl/zpl_printer.py
zpl/zpl_render_table.py
zpl/zpl_render_text.py
zpl/zpl_text_utils.py
zpl/zpl_to_pdf.py
zpl/zpl_utilities.py
zpl/zpl_utils.py
waproprint-0.1.1.dist-info/METADATA
waproprint-0.1.1.dist-info/WHEEL
waproprint-0.1.1.dist-info/entry_points.txt
waproprint-0.1.1.dist-info/RECORD
