Metadata-Version: 2.3
Name: waproprint
Version: 0.1.1
Summary: A tool for generating and printing documents from database queries
License: MIT
Author: Tom
Requires-Python: >=3.8,<4.0
Classifier: License :: OSI Approved :: MIT License
Classifier: Programming Language :: Python :: 3
Classifier: Programming Language :: Python :: 3.8
Classifier: Programming Language :: Python :: 3.9
Classifier: Programming Language :: Python :: 3.10
Classifier: Programming Language :: Python :: 3.11
Classifier: Programming Language :: Python :: 3.12
Classifier: Programming Language :: Python :: 3.13
Requires-Dist: cssutils (>=2.9.0,<3.0.0)
Requires-Dist: html2image (>=2.0.3.3)
Requires-Dist: html2text (>=2020.1.16,<2021.0.0)
Requires-Dist: jinja2 (>=3.0.0)
Requires-Dist: pdfkit (>=1.0.0)
Requires-Dist: playwright (>=1.42.0,<2.0.0)
Requires-Dist: pymssql (>=2.2.7,<3.0.0)
Requires-Dist: pyodbc (>=4.0.0)
Requires-Dist: pypdf2 (>=2.0.0)
Requires-Dist: python-dotenv (>=0.19.0)
Requires-Dist: reportlab (>=3.6.8)
Requires-Dist: tabulate (>=0.9.0,<0.10.0)
Requires-Dist: tinycss (>=0.4,<0.5)
Requires-Dist: wand (>=0.6.7)
